Metadata-Version: 2.1
Name: pyestimate
Version: 0.3.1
Summary: Sinusoidal parameters estimators (1D, 2D, single or multiple sinusoids, ...)
Home-page: https://github.com/alexishumblet/pyestimate
Author: Alexis Humblet
Author-email: alexishumblet@gmail.com
License: BSD 3-clause
Classifier: Development Status :: 4 - Beta
Classifier: Intended Audience :: Science/Research
Classifier: License :: OSI Approved :: BSD License
License-File: LICENSE
